<?xml version="1.0" encoding="UTF-8"?>
<EC_BLAST>
  <ANNOTATION>
    <MAPPING STATUS="SELECTED">
      <AAM>[CH:7](=[CH:25][CH:24]=[C:22]([CH:28]=[CH:14][CH:13]=[C:12]([CH:15]=[CH:30][C:6]1=[C:34]([CH3:40])[CH2:9][CH2:10][CH2:19][C:23]1([CH3:35])[CH3:36])[CH3:11])[CH3:1])[CH:3]=[C:29]([CH:18]=[CH:38][CH:4]=[C:39]([CH:26]=[CH:32][C:16]2=[C:27]([CH3:8])[CH2:2][CH2:33][CH2:37][C:31]2([CH3:17])[CH3:20])[CH3:21])[CH3:5].[O:41]=[O:42]&gt;&gt;[O:41]=[CH:25][CH:24]=[C:22]([CH:28]=[CH:14][CH:13]=[C:12]([CH:15]=[CH:30][C:6]1=[C:34]([CH3:40])[CH2:9][CH2:10][CH2:19][C:23]1([CH3:35])[CH3:36])[CH3:11])[CH3:1].[O:42]=[CH:7][CH:3]=[C:29]([CH:18]=[CH:38][CH:4]=[C:39]([CH:26]=[CH:32][C:16]1=[C:27]([CH3:8])[CH2:2][CH2:33][CH2:37][C:31]1([CH3:17])[CH3:20])[CH3:21])[CH3:5]</AAM>
    </MAPPING>
    <MAPPING ALGORTIHM="Local Minimization Model">
      <AAM>[CH:7](=[CH:25][CH:24]=[C:22]([CH:28]=[CH:14][CH:13]=[C:12]([CH:15]=[CH:30][C:6]1=[C:34]([CH3:40])[CH2:9][CH2:10][CH2:19][C:23]1([CH3:35])[CH3:36])[CH3:11])[CH3:1])[CH:3]=[C:29]([CH:18]=[CH:38][CH:4]=[C:39]([CH:26]=[CH:32][C:16]2=[C:27]([CH3:8])[CH2:2][CH2:33][CH2:37][C:31]2([CH3:17])[CH3:20])[CH3:21])[CH3:5].[O:41]=[O:42]&gt;&gt;[O:41]=[CH:25][CH:24]=[C:22]([CH:28]=[CH:14][CH:13]=[C:12]([CH:15]=[CH:30][C:6]1=[C:34]([CH3:40])[CH2:9][CH2:10][CH2:19][C:23]1([CH3:35])[CH3:36])[CH3:11])[CH3:1].[O:42]=[CH:7][CH:3]=[C:29]([CH:18]=[CH:38][CH:4]=[C:39]([CH:26]=[CH:32][C:16]1=[C:27]([CH3:8])[CH2:2][CH2:33][CH2:37][C:31]1([CH3:17])[CH3:20])[CH3:21])[CH3:5]</AAM>
      <SCORE>4</SCORE>
      <CHAOS>0 &lt;=&gt; 51</CHAOS>
      <SIGMA>1</SIGMA>
      <ENERGY>27E02</ENERGY>
      <DELTA>27E02</DELTA>
    </MAPPING>
    <MAPPING ALGORTIHM="Global Maximization Model">
      <AAM>[CH:7](=[CH:25][CH:24]=[C:22]([CH:28]=[CH:14][CH:13]=[C:12]([CH:15]=[CH:30][C:6]1=[C:34]([CH3:40])[CH2:9][CH2:10][CH2:19][C:23]1([CH3:35])[CH3:36])[CH3:11])[CH3:1])[CH:3]=[C:29]([CH:18]=[CH:38][CH:4]=[C:39]([CH:26]=[CH:32][C:16]2=[C:27]([CH3:8])[CH2:2][CH2:33][CH2:37][C:31]2([CH3:17])[CH3:20])[CH3:21])[CH3:5].[O:41]=[O:42]&gt;&gt;[O:41]=[CH:25][CH:24]=[C:22]([CH:28]=[CH:14][CH:13]=[C:12]([CH:15]=[CH:30][C:6]1=[C:34]([CH3:40])[CH2:9][CH2:10][CH2:19][C:23]1([CH3:35])[CH3:36])[CH3:11])[CH3:1].[O:42]=[CH:7][CH:3]=[C:29]([CH:18]=[CH:38][CH:4]=[C:39]([CH:26]=[CH:32][C:16]1=[C:27]([CH3:8])[CH2:2][CH2:33][CH2:37][C:31]1([CH3:17])[CH3:20])[CH3:21])[CH3:5]</AAM>
      <SCORE>4</SCORE>
      <CHAOS>0 &lt;=&gt; 51</CHAOS>
      <SIGMA>1</SIGMA>
      <ENERGY>27E02</ENERGY>
      <DELTA>27E02</DELTA>
    </MAPPING>
    <MAPPING ALGORTIHM="Max-Mixture Model">
      <AAM>[CH:7](=[CH:25][CH:24]=[C:22]([CH:28]=[CH:14][CH:13]=[C:12]([CH:15]=[CH:30][C:6]1=[C:34]([CH3:40])[CH2:9][CH2:10][CH2:19][C:23]1([CH3:35])[CH3:36])[CH3:11])[CH3:1])[CH:3]=[C:29]([CH:18]=[CH:38][CH:4]=[C:39]([CH:26]=[CH:32][C:16]2=[C:27]([CH3:8])[CH2:2][CH2:33][CH2:37][C:31]2([CH3:17])[CH3:20])[CH3:21])[CH3:5].[O:41]=[O:42]&gt;&gt;[O:41]=[CH:25][CH:24]=[C:22]([CH:28]=[CH:14][CH:13]=[C:12]([CH:15]=[CH:30][C:6]1=[C:34]([CH3:40])[CH2:9][CH2:10][CH2:19][C:23]1([CH3:35])[CH3:36])[CH3:11])[CH3:1].[O:42]=[CH:7][CH:3]=[C:29]([CH:18]=[CH:38][CH:4]=[C:39]([CH:26]=[CH:32][C:16]1=[C:27]([CH3:8])[CH2:2][CH2:33][CH2:37][C:31]1([CH3:17])[CH3:20])[CH3:21])[CH3:5]</AAM>
      <SCORE>4</SCORE>
      <CHAOS>0 &lt;=&gt; 51</CHAOS>
      <SIGMA>1</SIGMA>
      <ENERGY>27E02</ENERGY>
      <DELTA>27E02</DELTA>
    </MAPPING>
    <MAPPING ALGORTIHM="Ring Conservation Model">
      <AAM>[CH:7](=[CH:25][CH:24]=[C:22]([CH:28]=[CH:14][CH:13]=[C:12]([CH:15]=[CH:30][C:6]1=[C:34]([CH3:40])[CH2:9][CH2:10][CH2:19][C:23]1([CH3:35])[CH3:36])[CH3:11])[CH3:1])[CH:3]=[C:29]([CH:18]=[CH:38][CH:4]=[C:39]([CH:26]=[CH:32][C:16]2=[C:27]([CH3:8])[CH2:2][CH2:33][CH2:37][C:31]2([CH3:17])[CH3:20])[CH3:21])[CH3:5].[O:41]=[O:42]&gt;&gt;[O:41]=[CH:25][CH:24]=[C:22]([CH:28]=[CH:14][CH:13]=[C:12]([CH:15]=[CH:30][C:6]1=[C:34]([CH3:40])[CH2:9][CH2:10][CH2:19][C:23]1([CH3:35])[CH3:36])[CH3:11])[CH3:1].[O:42]=[CH:7][CH:3]=[C:29]([CH:18]=[CH:38][CH:4]=[C:39]([CH:26]=[CH:32][C:16]1=[C:27]([CH3:8])[CH2:2][CH2:33][CH2:37][C:31]1([CH3:17])[CH3:20])[CH3:21])[CH3:5]</AAM>
      <SCORE>4</SCORE>
      <CHAOS>0 &lt;=&gt; 51</CHAOS>
      <SIGMA>1</SIGMA>
      <ENERGY>27E02</ENERGY>
      <DELTA>27E02</DELTA>
    </MAPPING>
  </ANNOTATION>
</EC_BLAST>
