<?xml version="1.0" encoding="UTF-8"?><EC_BLAST>
  <ANNOTATION>
    <FINGERPRINTS BC="1">
      <FORMED_CLEAVED>[O-P:4.0]</FORMED_CLEAVED>
    </FINGERPRINTS>
    <FINGERPRINTS RC="2">
      <CENTRE>[[C]COP(=O)([O-])[O-]&gt;&gt;[O]P(=O)([O-])OP(=O)([O-])OC[C]:1.0, [C]OP(=O)([O-])OP(=O)([O-])O[C]&gt;&gt;[C]OP(=O)([O-])[O-]:1.0, [C]OP(=O)([O-])O[P]:2.0, [C]OP(=O)([O-])O[P]&gt;&gt;[C]OP(=O)([O-])OP(=O)([O-])O[C]:1.0, [C]OP(=O)([O-])O[P]&gt;&gt;[C]OP(=O)([O-])O[P]:1.0, [C]OP(=O)([O-])[O-]:1.0, [C]OP(=O)([O-])[O-]&gt;&gt;[C]OP(=O)([O-])O[P]:1.0, [C]OP(=O)([O-])[O-]&gt;&gt;[P]OP(=O)([O-])O[C]:1.0, [O-]:4.0, [O]:2.0, [O]C(OP(=O)([O-])OP(=O)([O-])[O])[C]&gt;&gt;[O]C(OP(=O)([O-])OP(=O)([O-])[O])[C]:1.0, [O]P(=O)([O-])OP(=O)([O-])[O]:2.0, [O]P(=O)([O-])OP(=O)([O-])[O]&gt;&gt;[O]P(=O)([O-])[O-]:1.0, [O]P(=O)([O-])[O-]:3.0, [O]P(=O)([O-])[O-]&gt;&gt;[O]P(=O)([O-])[O]:2.0, [O]P(=O)([O-])[O]:5.0, [O]P(=O)([O-])[O]&gt;&gt;[O]P(=O)([O-])OP(=O)([O-])[O]:1.0, [O]P(=O)([O-])[O]&gt;&gt;[O]P(=O)([O-])[O]:1.0, [P]:4.0, [P]OP(=O)([O-])O[C]:1.0, [P]O[P]:2.0, [P]O[P]&gt;&gt;[P][O-]:1.0, [P][O-]:4.0, [P][O-]&gt;&gt;[P]O[P]:1.0, [P][O-]&gt;&gt;[P][O-]:1.0]</CENTRE>
    </FINGERPRINTS>
    <MAPPING STATUS="SELECTED">
      <AAM>[O:132]=[P:131]([O-:133])([O-:134])[O:92][CH2:94][CH:130]=[C:129]([CH3:90])[CH2:96][CH2:98][CH:128]=[C:127]([CH3:88])[CH2:99][CH2:102][CH:126]=[C:125]([CH3:135])[CH2:104][CH2:105][CH:124]=[C:123]([CH3:86])[CH2:107][CH2:109][CH:122]=[C:121]([CH3:136])[CH2:111][CH2:113][CH:120]=[C:119]([CH3:84])[CH2:115][CH2:118][CH:117]=[C:116]([CH3:137])[CH2:114][CH2:112][CH:110]=[C:108]([CH3:83])[CH2:106][CH2:103][CH:101]=[C:100]([CH3:79])[CH2:97][CH2:95][CH:93]=[C:91]([CH3:80])[CH2:89][CH2:87][CH:78]=[C:81]([CH3:82])[CH3:85].[O:57]=[c:56]1[cH:55][cH:52][n:51]([c:59](=[O:54])[nH:58]1)[CH:49]2[O:47][CH:45]([CH2:40][O:38][P:36](=[O:37])([O-:39])[O:34][P:31](=[O:32])([O-:33])[O:29][CH:27]3[O:26][CH:77]([CH2:25][OH:19])[CH:15]([OH:11])[CH:70]([O:66][CH:65]([C:62](=[O:63])[NH:46][CH:44]([C:43](=[O:41])[NH:42][CH:35]([C:71](=[O:72])[O-:73])[CH2:74][CH2:30][C:75](=[O:76])[NH:28][CH:20]([C:22](=[O:23])[NH:24][CH:21]([C:7](=[O:6])[NH:4][CH:3]([C:2](=[O:1])[O-:5])[CH3:8])[CH3:9])[CH2:10][CH2:17][CH2:16][CH2:18][NH3+:12])[CH3:13])[CH3:14])[CH:48]3[NH:64][C:67](=[O:68])[CH3:69])[CH:61]([OH:50])[CH:53]2[OH:60]&gt;&gt;[O:1]=[C:2]([O-:5])[CH:3]([NH:4][C:7](=[O:6])[CH:21]([NH:24][C:22](=[O:23])[CH:20]([NH:28][C:75](=[O:76])[CH2:30][CH2:74][CH:35]([NH:42][C:43](=[O:41])[CH:44]([NH:46][C:62](=[O:63])[CH:65]([O:66][CH:70]1[CH:15]([OH:11])[CH:77]([O:26][CH:27]([O:29][P:31](=[O:32])([O-:133])[O:33][P:131](=[O:132])([O-:134])[O:92][CH2:94][CH:130]=[C:129]([CH3:90])[CH2:96][CH2:98][CH:128]=[C:127]([CH3:88])[CH2:99][CH2:102][CH:126]=[C:125]([CH3:135])[CH2:104][CH2:105][CH:124]=[C:123]([CH3:86])[CH2:107][CH2:109][CH:122]=[C:121]([CH3:136])[CH2:111][CH2:113][CH:120]=[C:119]([CH3:84])[CH2:115][CH2:118][CH:117]=[C:116]([CH3:137])[CH2:114][CH2:112][CH:110]=[C:108]([CH3:83])[CH2:106][CH2:103][CH:101]=[C:100]([CH3:79])[CH2:97][CH2:95][CH:93]=[C:91]([CH3:80])[CH2:89][CH2:87][CH:78]=[C:81]([CH3:85])[CH3:82])[CH:48]1[NH:64][C:67](=[O:68])[CH3:69])[CH2:25][OH:19])[CH3:14])[CH3:13])[C:71](=[O:72])[O-:73])[CH2:10][CH2:17][CH2:16][CH2:18][NH3+:12])[CH3:9])[CH3:8].[O:57]=[c:56]1[cH:55][cH:52][n:51]([c:59](=[O:54])[nH:58]1)[CH:49]2[O:47][CH:45]([CH2:40][O:38][P:36](=[O:37])([O-:34])[O-:39])[CH:61]([OH:50])[CH:53]2[OH:60]</AAM>
    </MAPPING>
    <MAPPING ALGORTIHM="Local Minimization Model">
      <AAM>[O:132]=[P:131]([O-:133])([O-:134])[O:92][CH2:94][CH:130]=[C:129]([CH3:90])[CH2:96][CH2:98][CH:128]=[C:127]([CH3:88])[CH2:99][CH2:102][CH:126]=[C:125]([CH3:135])[CH2:104][CH2:105][CH:124]=[C:123]([CH3:86])[CH2:107][CH2:109][CH:122]=[C:121]([CH3:136])[CH2:111][CH2:113][CH:120]=[C:119]([CH3:84])[CH2:115][CH2:118][CH:117]=[C:116]([CH3:137])[CH2:114][CH2:112][CH:110]=[C:108]([CH3:83])[CH2:106][CH2:103][CH:101]=[C:100]([CH3:79])[CH2:97][CH2:95][CH:93]=[C:91]([CH3:80])[CH2:89][CH2:87][CH:78]=[C:81]([CH3:82])[CH3:85].[O:57]=[c:56]1[cH:55][cH:52][n:51]([c:59](=[O:54])[nH:58]1)[CH:49]2[O:47][CH:45]([CH2:40][O:38][P:36](=[O:37])([O-:39])[O:34][P:31](=[O:32])([O-:33])[O:29][CH:27]3[O:26][CH:77]([CH2:25][OH:19])[CH:15]([OH:11])[CH:70]([O:66][CH:65]([C:62](=[O:63])[NH:46][CH:44]([C:43](=[O:41])[NH:42][CH:35]([C:71](=[O:72])[O-:73])[CH2:74][CH2:30][C:75](=[O:76])[NH:28][CH:20]([C:22](=[O:23])[NH:24][CH:21]([C:7](=[O:6])[NH:4][CH:3]([C:2](=[O:1])[O-:5])[CH3:8])[CH3:9])[CH2:10][CH2:17][CH2:16][CH2:18][NH3+:12])[CH3:13])[CH3:14])[CH:48]3[NH:64][C:67](=[O:68])[CH3:69])[CH:61]([OH:50])[CH:53]2[OH:60]&gt;&gt;[O:1]=[C:2]([O-:5])[CH:3]([NH:4][C:7](=[O:6])[CH:21]([NH:24][C:22](=[O:23])[CH:20]([NH:28][C:75](=[O:76])[CH2:30][CH2:74][CH:35]([NH:42][C:43](=[O:41])[CH:44]([NH:46][C:62](=[O:63])[CH:65]([O:66][CH:70]1[CH:15]([OH:11])[CH:77]([O:26][CH:27]([O:29][P:31](=[O:32])([O-:133])[O:33][P:131](=[O:132])([O-:134])[O:92][CH2:94][CH:130]=[C:129]([CH3:90])[CH2:96][CH2:98][CH:128]=[C:127]([CH3:88])[CH2:99][CH2:102][CH:126]=[C:125]([CH3:135])[CH2:104][CH2:105][CH:124]=[C:123]([CH3:86])[CH2:107][CH2:109][CH:122]=[C:121]([CH3:136])[CH2:111][CH2:113][CH:120]=[C:119]([CH3:84])[CH2:115][CH2:118][CH:117]=[C:116]([CH3:137])[CH2:114][CH2:112][CH:110]=[C:108]([CH3:83])[CH2:106][CH2:103][CH:101]=[C:100]([CH3:79])[CH2:97][CH2:95][CH:93]=[C:91]([CH3:80])[CH2:89][CH2:87][CH:78]=[C:81]([CH3:85])[CH3:82])[CH:48]1[NH:64][C:67](=[O:68])[CH3:69])[CH2:25][OH:19])[CH3:14])[CH3:13])[C:71](=[O:72])[O-:73])[CH2:10][CH2:17][CH2:16][CH2:18][NH3+:12])[CH3:9])[CH3:8].[O:57]=[c:56]1[cH:55][cH:52][n:51]([c:59](=[O:54])[nH:58]1)[CH:49]2[O:47][CH:45]([CH2:40][O:38][P:36](=[O:37])([O-:34])[O-:39])[CH:61]([OH:50])[CH:53]2[OH:60]</AAM>
      <SCORE>4</SCORE>
      <CHAOS>0 &lt;=&gt; 142</CHAOS>
      <SIGMA>0</SIGMA>
      <ENERGY>13E02</ENERGY>
      <DELTA>13E02</DELTA>
    </MAPPING>
    <MAPPING ALGORTIHM="Global Maximization Model">
      <AAM>[O:55]=[P:54]([O-:56])([O-:57])[O:15][CH2:17][CH:53]=[C:52]([CH3:13])[CH2:19][CH2:21][CH:51]=[C:50]([CH3:11])[CH2:22][CH2:25][CH:49]=[C:48]([CH3:58])[CH2:27][CH2:28][CH:47]=[C:46]([CH3:9])[CH2:30][CH2:32][CH:45]=[C:44]([CH3:59])[CH2:34][CH2:36][CH:43]=[C:42]([CH3:7])[CH2:38][CH2:41][CH:40]=[C:39]([CH3:60])[CH2:37][CH2:35][CH:33]=[C:31]([CH3:6])[CH2:29][CH2:26][CH:24]=[C:23]([CH3:2])[CH2:20][CH2:18][CH:16]=[C:14]([CH3:3])[CH2:12][CH2:10][CH:1]=[C:4]([CH3:5])[CH3:8].[O:117]=[c:116]1[cH:115][cH:112][n:111]([c:119](=[O:114])[nH:118]1)[CH:109]2[O:107][CH:105]([CH2:100][O:98][P:96](=[O:97])([O-:99])[O:94][P:91](=[O:92])([O-:93])[O:89][CH:87]3[O:86][CH:137]([CH2:85][OH:79])[CH:75]([OH:71])[CH:130]([O:126][CH:125]([C:122](=[O:123])[NH:106][CH:104]([C:103](=[O:101])[NH:102][CH:95]([C:131](=[O:132])[O-:133])[CH2:134][CH2:90][C:135](=[O:136])[NH:88][CH:80]([C:82](=[O:83])[NH:84][CH:81]([C:67](=[O:66])[NH:64][CH:63]([C:62](=[O:61])[O-:65])[CH3:68])[CH3:69])[CH2:70][CH2:77][CH2:76][CH2:78][NH3+:72])[CH3:73])[CH3:74])[CH:108]3[NH:124][C:127](=[O:128])[CH3:129])[CH:121]([OH:110])[CH:113]2[OH:120]&gt;&gt;[O:61]=[C:62]([O-:65])[CH:63]([NH:64][C:67](=[O:66])[CH:81]([NH:84][C:82](=[O:83])[CH:80]([NH:88][C:135](=[O:136])[CH2:90][CH2:134][CH:95]([NH:102][C:103](=[O:101])[CH:104]([NH:106][C:122](=[O:123])[CH:125]([O:126][CH:130]1[CH:75]([OH:71])[CH:137]([O:86][CH:87]([O:89][P:91](=[O:92])([O-:94])[O:56][P:54](=[O:55])([O-:57])[O:15][CH2:17][CH:53]=[C:52]([CH3:13])[CH2:19][CH2:21][CH:51]=[C:50]([CH3:11])[CH2:22][CH2:25][CH:49]=[C:48]([CH3:58])[CH2:27][CH2:28][CH:47]=[C:46]([CH3:9])[CH2:30][CH2:32][CH:45]=[C:44]([CH3:59])[CH2:34][CH2:36][CH:43]=[C:42]([CH3:7])[CH2:38][CH2:41][CH:40]=[C:39]([CH3:60])[CH2:37][CH2:35][CH:33]=[C:31]([CH3:6])[CH2:29][CH2:26][CH:24]=[C:23]([CH3:2])[CH2:20][CH2:18][CH:16]=[C:14]([CH3:3])[CH2:12][CH2:10][CH:1]=[C:4]([CH3:5])[CH3:8])[CH:108]1[NH:124][C:127](=[O:128])[CH3:129])[CH2:85][OH:79])[CH3:74])[CH3:73])[C:131](=[O:132])[O-:133])[CH2:70][CH2:77][CH2:76][CH2:78][NH3+:72])[CH3:69])[CH3:68].[O:117]=[c:116]1[cH:115][cH:112][n:111]([c:119](=[O:114])[nH:118]1)[CH:109]2[O:107][CH:105]([CH2:100][O:98][P:96](=[O:97])([O-:93])[O-:99])[CH:121]([OH:110])[CH:113]2[OH:120]</AAM>
      <SCORE>4</SCORE>
      <CHAOS>0 &lt;=&gt; 140</CHAOS>
      <SIGMA>0</SIGMA>
      <ENERGY>13E02</ENERGY>
      <DELTA>13E02</DELTA>
    </MAPPING>
    <MAPPING ALGORTIHM="Max-Mixture Model">
      <AAM>[H:150][CH:5]([H:152])[C:4](=[CH:1][CH2:10][CH2:12][C:14](=[CH:16][CH2:18][CH2:20][C:23](=[CH:24][CH2:26][CH2:29][C:31](=[CH:33][CH2:35][CH2:37][C:39](=[CH:40][CH2:41][CH2:38][C:42](=[CH:43][CH2:36][CH2:34][C:44](=[CH:45][CH2:32][CH2:30][C:46](=[CH:47][CH2:28][CH2:27][C:48](=[CH:49][CH2:25][CH2:22][C:50](=[CH:51][CH2:21][CH2:19][C:52](=[CH:53][CH2:17][O:15][P:54](=[O:55])([O-:56])[O-:57])[CH3:13])[CH3:11])[CH3:58])[CH3:9])[CH3:59])[CH3:7])[CH3:60])[CH3:6])[CH3:2])[CH3:3])[CH:8]([H:157])[H:159].[H:276][C:121]1([OH:110])[CH:113]([OH:120])[CH:109]([O:107][CH:105]1[CH2:100][O:98][P:96](=[O:97])([O-:99])[O:94][P:91](=[O:92])([O-:93])[O:89][CH:87]2[O:86][CH:137]([CH2:85][OH:79])[CH:75]([OH:71])[CH:130]([O:126][CH:125]([C:122](=[O:123])[NH:106][CH:104]([C:103](=[O:101])[NH:102][CH:95]([C:131](=[O:132])[O-:133])[CH2:134][CH2:90][C:135](=[O:136])[NH:88][CH:80]([C:82](=[O:83])[NH:84][CH:81]([C:67](=[O:66])[NH:64][CH:63]([C:62](=[O:61])[O-:65])[CH3:68])[CH3:69])[CH2:70][CH2:77][CH2:76][CH2:78][NH3+:72])[CH3:73])[CH3:74])[CH:108]2[NH:124][C:127](=[O:128])[CH3:129])[n:111]3[cH:112][cH:115][c:116](=[O:117])[nH:118][c:119]3=[O:114]&gt;&gt;[H:159][CH2:12][C:14](=[CH:16][CH2:18][CH2:20][C:23](=[CH:24][CH2:26][CH2:29][C:31](=[CH:33][CH2:35][CH2:37][C:39](=[CH:40][CH2:41][CH2:38][C:42](=[CH:43][CH2:36][CH2:34][C:44](=[CH:45][CH2:32][CH2:30][C:46](=[CH:47][CH2:28][CH2:27][C:48](=[CH:49][CH2:25][CH2:22][C:50](=[CH:51][CH2:21][CH2:19][C:52](=[CH:53][CH:109]([H:157])[CH:113]([H:152])[C:121](=[CH:105][CH2:100][O:98][P:96](=[O:97])([O-:99])[O:94][P:91](=[O:92])([O-:93])[O:89][CH:87]1[O:86][CH:137]([CH2:85][OH:79])[CH:75]([OH:71])[CH:130]([O:126][CH:125]([C:122](=[O:123])[NH:106][CH:104]([C:103](=[O:101])[NH:102][CH:95]([C:131](=[O:132])[O-:133])[CH2:134][CH2:90][C:135](=[O:136])[NH:88][CH:80]([C:82](=[O:83])[NH:84][CH:81]([C:67](=[O:66])[NH:64][CH:63]([C:62](=[O:61])[O-:65])[CH3:68])[CH3:69])[CH2:70][CH2:77][CH2:76][CH2:78][NH3+:72])[CH3:73])[CH3:74])[CH:108]1[NH:124][C:127](=[O:128])[CH3:129])[CH2:17][H:150])[CH3:13])[CH3:11])[CH3:58])[CH3:9])[CH3:59])[CH3:7])[CH3:60])[CH3:6])[CH3:2])[CH3:3].[H:276][C:4]1([OH:110])[CH:8]([OH:120])[CH:5]([O:107][CH:1]1[CH2:10][O:15][P:54](=[O:55])([O-:56])[O-:57])[n:111]2[cH:112][cH:115][c:116](=[O:117])[nH:118][c:119]2=[O:114]</AAM>
      <SCORE>30</SCORE>
      <CHAOS>0 &lt;=&gt; 582</CHAOS>
      <SIGMA>6</SIGMA>
      <ENERGY>62E02</ENERGY>
      <DELTA>1E04</DELTA>
    </MAPPING>
    <MAPPING ALGORTIHM="Ring Conservation Model">
      <AAM>[H:212][CH:82]([H:214])[C:81](=[CH:78][CH2:87][CH2:89][C:91](=[CH:93][CH2:95][CH2:97][C:100](=[CH:101][CH2:103][CH2:106][C:108](=[CH:110][CH2:112][CH2:114][C:116](=[CH:117][CH2:118][CH2:115][C:119](=[CH:120][CH2:113][CH2:111][C:121](=[CH:122][CH2:109][CH2:107][C:123](=[CH:124][CH2:105][CH2:104][C:125](=[CH:126][CH2:102][CH2:99][C:127](=[CH:128][CH2:98][CH2:96][C:129](=[CH:130][CH2:94][O:92][P:131](=[O:132])([O-:133])[O-:134])[CH3:90])[CH3:88])[CH3:135])[CH3:86])[CH3:136])[CH3:84])[CH3:137])[CH3:83])[CH3:79])[CH3:80])[CH:85]([H:219])[H:221].[H:187][C:61]1([OH:50])[CH:53]([OH:60])[CH:49]([O:47][CH:45]1[CH2:40][O:38][P:36](=[O:37])([O-:39])[O:34][P:31](=[O:32])([O-:33])[O:29][CH:27]2[O:26][CH:77]([CH2:25][OH:19])[CH:15]([OH:11])[CH:70]([O:66][CH:65]([C:62](=[O:63])[NH:46][CH:44]([C:43](=[O:41])[NH:42][CH:35]([C:71](=[O:72])[O-:73])[CH2:74][CH2:30][C:75](=[O:76])[NH:28][CH:20]([C:22](=[O:23])[NH:24][CH:21]([C:7](=[O:6])[NH:4][CH:3]([C:2](=[O:1])[O-:5])[CH3:8])[CH3:9])[CH2:10][CH2:17][CH2:16][CH2:18][NH3+:12])[CH3:13])[CH3:14])[CH:48]2[NH:64][C:67](=[O:68])[CH3:69])[n:51]3[cH:52][cH:55][c:56](=[O:57])[nH:58][c:59]3=[O:54]&gt;&gt;[H:221][CH2:89][C:91](=[CH:93][CH2:95][CH2:97][C:100](=[CH:101][CH2:103][CH2:106][C:108](=[CH:110][CH2:112][CH2:114][C:116](=[CH:117][CH2:118][CH2:115][C:119](=[CH:120][CH2:113][CH2:111][C:121](=[CH:122][CH2:109][CH2:107][C:123](=[CH:124][CH2:105][CH2:104][C:125](=[CH:126][CH2:102][CH2:99][C:127](=[CH:128][CH2:98][CH2:96][C:129](=[CH:130][CH:49]([H:219])[CH:53]([H:214])[C:61](=[CH:45][CH2:40][O:38][P:36](=[O:37])([O-:39])[O:34][P:31](=[O:32])([O-:33])[O:29][CH:27]1[O:26][CH:77]([CH2:25][OH:19])[CH:15]([OH:11])[CH:70]([O:66][CH:65]([C:62](=[O:63])[NH:46][CH:44]([C:43](=[O:41])[NH:42][CH:35]([C:71](=[O:72])[O-:73])[CH2:74][CH2:30][C:75](=[O:76])[NH:28][CH:20]([C:22](=[O:23])[NH:24][CH:21]([C:7](=[O:6])[NH:4][CH:3]([C:2](=[O:1])[O-:5])[CH3:8])[CH3:9])[CH2:10][CH2:17][CH2:16][CH2:18][NH3+:12])[CH3:13])[CH3:14])[CH:48]1[NH:64][C:67](=[O:68])[CH3:69])[CH2:94][H:212])[CH3:90])[CH3:88])[CH3:135])[CH3:86])[CH3:136])[CH3:84])[CH3:137])[CH3:83])[CH3:79])[CH3:80].[H:187][C:81]1([OH:50])[CH:85]([OH:60])[CH:82]([O:47][CH:78]1[CH2:87][O:92][P:131](=[O:132])([O-:133])[O-:134])[n:51]2[cH:52][cH:55][c:56](=[O:57])[nH:58][c:59]2=[O:54]</AAM>
      <SCORE>30</SCORE>
      <CHAOS>0 &lt;=&gt; 582</CHAOS>
      <SIGMA>6</SIGMA>
      <ENERGY>62E02</ENERGY>
      <DELTA>1E04</DELTA>
    </MAPPING>
  </ANNOTATION>
</EC_BLAST>
