<?xml version="1.0" encoding="UTF-8"?>
<EC_BLAST>
  <ANNOTATION>
    <MAPPING STATUS="SELECTED">
      <AAM>[O:14]=[C:6]([O-:18])[CH:22]([NH3+:11])[CH2:2][C:8](=[O:7])[NH:20][CH:21]1[O:4][CH:15]([CH2:3][OH:9])[CH:19]([OH:23])[CH:12]([OH:16])[CH:10]1[NH:1][C:13](=[O:5])[CH3:17].[H:46][O:24][H:47]&gt;&gt;[H:46][NH:20][CH:21]1[O:4][CH:15]([CH2:3][OH:9])[CH:19]([OH:23])[CH:12]([OH:16])[CH:10]1[NH:1][C:13](=[O:5])[CH3:17].[O:7]=[C:8]([O-:24])[CH2:2][CH:22]([C:6](=[O:14])[O-:18])[NH3+:11].[H+:47]</AAM>
    </MAPPING>
    <MAPPING ALGORTIHM="Local Minimization Model">
      <AAM>[O:14]=[C:6]([O-:18])[CH:22]([NH3+:11])[CH2:2][C:8](=[O:7])[NH:20][CH:21]1[O:4][CH:15]([CH2:3][OH:9])[CH:19]([OH:23])[CH:12]([OH:16])[CH:10]1[NH:1][C:13](=[O:5])[CH3:17].[H:46][O:24][H:47]&gt;&gt;[H:46][NH:20][CH:21]1[O:4][CH:15]([CH2:3][OH:9])[CH:19]([OH:23])[CH:12]([OH:16])[CH:10]1[NH:1][C:13](=[O:5])[CH3:17].[O:7]=[C:8]([O-:24])[CH2:2][CH:22]([C:6](=[O:14])[O-:18])[NH3+:11].[H+:47]</AAM>
      <SCORE>5</SCORE>
      <CHAOS>0 &lt;=&gt; 18</CHAOS>
      <SIGMA>0</SIGMA>
      <ENERGY>6.6E02</ENERGY>
      <DELTA>20E02</DELTA>
    </MAPPING>
    <MAPPING ALGORTIHM="Global Maximization Model">
      <AAM>[O:14]=[C:6]([O-:18])[CH:22]([NH3+:11])[CH2:2][C:8](=[O:7])[NH:20][CH:21]1[O:4][CH:15]([CH2:3][OH:9])[CH:19]([OH:23])[CH:12]([OH:16])[CH:10]1[NH:1][C:13](=[O:5])[CH3:17].[H:46][O:24][H:47]&gt;&gt;[H:46][NH:20][CH:21]1[O:4][CH:15]([CH2:3][OH:9])[CH:19]([OH:23])[CH:12]([OH:16])[CH:10]1[NH:1][C:13](=[O:5])[CH3:17].[O:7]=[C:8]([O-:24])[CH2:2][CH:22]([C:6](=[O:14])[O-:18])[NH3+:11].[H+:47]</AAM>
      <SCORE>5</SCORE>
      <CHAOS>0 &lt;=&gt; 18</CHAOS>
      <SIGMA>0</SIGMA>
      <ENERGY>6.6E02</ENERGY>
      <DELTA>20E02</DELTA>
    </MAPPING>
    <MAPPING ALGORTIHM="Max-Mixture Model">
      <AAM>[O:14]=[C:6]([O-:18])[CH:22]([NH3+:11])[CH2:2][C:8](=[O:7])[NH:20][CH:21]1[O:4][CH:15]([CH2:3][OH:9])[CH:19]([OH:23])[CH:12]([OH:16])[CH:10]1[NH:1][C:13](=[O:5])[CH3:17].[H:46][O:24][H:47]&gt;&gt;[H:46][NH:20][CH:21]1[O:4][CH:15]([CH2:3][OH:9])[CH:19]([OH:23])[CH:12]([OH:16])[CH:10]1[NH:1][C:13](=[O:5])[CH3:17].[O:7]=[C:8]([O-:24])[CH2:2][CH:22]([C:6](=[O:14])[O-:18])[NH3+:11].[H+:47]</AAM>
      <SCORE>5</SCORE>
      <CHAOS>0 &lt;=&gt; 18</CHAOS>
      <SIGMA>0</SIGMA>
      <ENERGY>6.6E02</ENERGY>
      <DELTA>20E02</DELTA>
    </MAPPING>
    <MAPPING ALGORTIHM="Ring Conservation Model">
      <AAM>[O:14]=[C:6]([O-:18])[CH:22]([NH3+:11])[CH2:2][C:8](=[O:7])[NH:20][CH:21]1[O:4][CH:15]([CH2:3][OH:9])[CH:19]([OH:23])[CH:12]([OH:16])[CH:10]1[NH:1][C:13](=[O:5])[CH3:17].[H:46][O:24][H:47]&gt;&gt;[H:46][NH:20][CH:21]1[O:4][CH:15]([CH2:3][OH:9])[CH:19]([OH:23])[CH:12]([OH:16])[CH:10]1[NH:1][C:13](=[O:5])[CH3:17].[O:7]=[C:8]([O-:24])[CH2:2][CH:22]([C:6](=[O:14])[O-:18])[NH3+:11].[H+:47]</AAM>
      <SCORE>5</SCORE>
      <CHAOS>0 &lt;=&gt; 18</CHAOS>
      <SIGMA>0</SIGMA>
      <ENERGY>6.6E02</ENERGY>
      <DELTA>20E02</DELTA>
    </MAPPING>
  </ANNOTATION>
</EC_BLAST>
