<?xml version="1.0" encoding="UTF-8"?>
<EC_BLAST>
  <ANNOTATION>
    <MAPPING STATUS="SELECTED">
      <AAM>[*:33][P:34](=[O:23])([O-:24])[O:7][P:30](=[O:12])([O-:9])[O:15][P:3](=[O:4])([O-:19])[O:26][CH2:5][CH:2]1[O:28][CH:20]([n:8]2[cH:13][n+:21]([c:11]3[c:35](=[O:27])[nH:31][c:6]([n:16][c:18]32)[N:29]([CH3:10])[CH3:32])[CH3:1])[CH:17]([OH:25])[CH:22]1[OH:14].[H:56][O:36][H:57]&gt;&gt;[O:27]=[c:35]1[nH:31][c:6]([n:16][c:18]2[c:11]1[n+:21]([cH:13][n:8]2[CH:20]3[O:28][CH:2]([CH2:5][O:26][P:3](=[O:4])([O-:15])[O-:19])[CH:22]([OH:14])[CH:17]3[OH:25])[CH3:1])[N:29]([CH3:10])[CH3:32].[*:33][P:34](=[O:23])([O-:24])[O:7][P:30](=[O:12])([O-:9])[O-:36].[H+:56].[H+:57]</AAM>
    </MAPPING>
    <MAPPING ALGORTIHM="Local Minimization Model">
      <AAM>[*:33][P:34](=[O:23])([O-:24])[O:7][P:30](=[O:12])([O-:9])[O:15][P:3](=[O:4])([O-:19])[O:26][CH2:5][CH:2]1[O:28][CH:20]([n:8]2[cH:13][n+:21]([c:11]3[c:35](=[O:27])[nH:31][c:6]([n:16][c:18]32)[N:29]([CH3:10])[CH3:32])[CH3:1])[CH:17]([OH:25])[CH:22]1[OH:14].[H:56][O:36][H:57]&gt;&gt;[O:27]=[c:35]1[nH:31][c:6]([n:16][c:18]2[c:11]1[n+:21]([cH:13][n:8]2[CH:20]3[O:28][CH:2]([CH2:5][O:26][P:3](=[O:4])([O-:19])[O-:36])[CH:22]([OH:14])[CH:17]3[OH:25])[CH3:1])[N:29]([CH3:10])[CH3:32].[*:33][P:34](=[O:23])([O-:24])[O:7][P:30](=[O:12])([O-:9])[O-:15].[H+:56].[H+:57]</AAM>
      <SCORE>4</SCORE>
      <CHAOS>0 &lt;=&gt; 12</CHAOS>
      <SIGMA>0</SIGMA>
      <ENERGY>6.7E02</ENERGY>
      <DELTA>16E02</DELTA>
    </MAPPING>
    <MAPPING ALGORTIHM="Global Maximization Model">
      <AAM>[*:33][P:34](=[O:23])([O-:24])[O:7][P:30](=[O:12])([O-:9])[O:15][P:3](=[O:4])([O-:19])[O:26][CH2:5][CH:2]1[O:28][CH:20]([n:8]2[cH:13][n+:21]([c:11]3[c:35](=[O:27])[nH:31][c:6]([n:16][c:18]32)[N:29]([CH3:10])[CH3:32])[CH3:1])[CH:17]([OH:25])[CH:22]1[OH:14].[H:56][O:36][H:57]&gt;&gt;[O:27]=[c:35]1[nH:31][c:6]([n:16][c:18]2[c:11]1[n+:21]([cH:13][n:8]2[CH:20]3[O:28][CH:2]([CH2:5][O:26][P:3](=[O:4])([O-:15])[O-:19])[CH:22]([OH:14])[CH:17]3[OH:25])[CH3:1])[N:29]([CH3:10])[CH3:32].[*:33][P:34](=[O:23])([O-:24])[O:7][P:30](=[O:12])([O-:9])[O-:36].[H+:56].[H+:57]</AAM>
      <SCORE>4</SCORE>
      <CHAOS>0 &lt;=&gt; 11</CHAOS>
      <SIGMA>0</SIGMA>
      <ENERGY>6.7E02</ENERGY>
      <DELTA>16E02</DELTA>
    </MAPPING>
    <MAPPING ALGORTIHM="Max-Mixture Model">
      <AAM>[*:33][P:34](=[O:23])([O-:24])[O:7][P:30](=[O:12])([O-:9])[O:15][P:3](=[O:4])([O-:19])[O:26][CH2:5][CH:2]1[O:28][CH:20]([n:8]2[cH:13][n+:21]([c:11]3[c:35](=[O:27])[nH:31][c:6]([n:16][c:18]32)[N:29]([CH3:10])[CH3:32])[CH3:1])[CH:17]([OH:25])[CH:22]1[OH:14].[H:56][O:36][H:57]&gt;&gt;[O:27]=[c:35]1[nH:31][c:6]([n:16][c:18]2[c:11]1[n+:21]([cH:13][n:8]2[CH:20]3[O:28][CH:2]([CH2:5][O:26][P:3](=[O:4])([O-:15])[O-:19])[CH:22]([OH:14])[CH:17]3[OH:25])[CH3:1])[N:29]([CH3:10])[CH3:32].[*:33][P:34](=[O:23])([O-:24])[O:7][P:30](=[O:12])([O-:9])[O-:36].[H+:56].[H+:57]</AAM>
      <SCORE>4</SCORE>
      <CHAOS>0 &lt;=&gt; 11</CHAOS>
      <SIGMA>0</SIGMA>
      <ENERGY>6.7E02</ENERGY>
      <DELTA>16E02</DELTA>
    </MAPPING>
    <MAPPING ALGORTIHM="Ring Conservation Model">
      <AAM>[*:33][P:34](=[O:23])([O-:24])[O:7][P:30](=[O:12])([O-:9])[O:15][P:3](=[O:4])([O-:19])[O:26][CH2:5][CH:2]1[O:28][CH:20]([n:8]2[cH:13][n+:21]([c:11]3[c:35](=[O:27])[nH:31][c:6]([n:16][c:18]32)[N:29]([CH3:10])[CH3:32])[CH3:1])[CH:17]([OH:25])[CH:22]1[OH:14].[H:56][O:36][H:57]&gt;&gt;[O:27]=[c:35]1[nH:31][c:6]([n:16][c:18]2[c:11]1[n+:21]([cH:13][n:8]2[CH:20]3[O:28][CH:2]([CH2:5][O:26][P:3](=[O:4])([O-:15])[O-:19])[CH:22]([OH:14])[CH:17]3[OH:25])[CH3:1])[N:29]([CH3:10])[CH3:32].[*:33][P:34](=[O:23])([O-:24])[O:7][P:30](=[O:12])([O-:9])[O-:36].[H+:56].[H+:57]</AAM>
      <SCORE>4</SCORE>
      <CHAOS>0 &lt;=&gt; 11</CHAOS>
      <SIGMA>0</SIGMA>
      <ENERGY>6.7E02</ENERGY>
      <DELTA>16E02</DELTA>
    </MAPPING>
  </ANNOTATION>
</EC_BLAST>
