<?xml version="1.0" encoding="UTF-8"?><EC_BLAST>
  <ANNOTATION>
    <MAPPING STATUS="SELECTED">
      <AAM>[O:34]=[P:33]([O-:35])([O-:7])[O:32][P:10](=[O:11])([O-:9])[O:13][CH2:31][CH2:14][CH:30]([CH3:16])[CH2:17][CH2:19][CH:20]=[C:24]([CH3:8])[CH2:29][CH2:28][CH:27]=[C:26]([CH3:3])[CH2:25][CH2:23][CH:22]=[C:21]([CH3:4])[CH2:18][CH2:15][CH:2]=[C:5]([CH3:6])[CH3:12].[H:37][OH:1]&gt;&gt;[O:11]=[P:10]([O-:9])([O-:32])[O:13][CH2:31][CH2:14][CH:30]([CH3:16])[CH2:17][CH2:19][CH:20]=[C:24]([CH3:8])[CH2:29][CH2:28][CH:27]=[C:26]([CH3:3])[CH2:25][CH2:23][CH:22]=[C:21]([CH3:4])[CH2:18][CH2:15][CH:2]=[C:5]([CH3:6])[CH3:12].[O:34]=[P:33]([O-:35])([O-:7])[OH:1].[H+:37]</AAM>
    </MAPPING>
    <MAPPING ALGORTIHM="Local Minimization Model">
      <AAM>[O:34]=[P:33]([O-:35])([O-:7])[O:32][P:10](=[O:11])([O-:9])[O:13][CH2:31][CH2:14][CH:30]([CH3:16])[CH2:17][CH2:19][CH:20]=[C:24]([CH3:8])[CH2:29][CH2:28][CH:27]=[C:26]([CH3:3])[CH2:25][CH2:23][CH:22]=[C:21]([CH3:4])[CH2:18][CH2:15][CH:2]=[C:5]([CH3:6])[CH3:12].[H:37][OH:1]&gt;&gt;[O:11]=[P:10]([O-:9])([O-:32])[O:13][CH2:31][CH2:14][CH:30]([CH3:16])[CH2:17][CH2:19][CH:20]=[C:24]([CH3:8])[CH2:29][CH2:28][CH:27]=[C:26]([CH3:3])[CH2:25][CH2:23][CH:22]=[C:21]([CH3:4])[CH2:18][CH2:15][CH:2]=[C:5]([CH3:6])[CH3:12].[O:34]=[P:33]([O-:35])([O-:7])[OH:1].[H+:37]</AAM>
      <SCORE>3</SCORE>
      <CHAOS>0 &lt;=&gt; 7</CHAOS>
      <SIGMA>0</SIGMA>
      <ENERGY>6.7E02</ENERGY>
      <DELTA>11E02</DELTA>
    </MAPPING>
    <MAPPING ALGORTIHM="Global Maximization Model">
      <AAM>[O:34]=[P:33]([O-:35])([O-:7])[O:32][P:10](=[O:11])([O-:9])[O:13][CH2:31][CH2:14][CH:30]([CH3:16])[CH2:17][CH2:19][CH:20]=[C:24]([CH3:8])[CH2:29][CH2:28][CH:27]=[C:26]([CH3:3])[CH2:25][CH2:23][CH:22]=[C:21]([CH3:4])[CH2:18][CH2:15][CH:2]=[C:5]([CH3:6])[CH3:12].[H:37][OH:1]&gt;&gt;[O:11]=[P:10]([O-:9])([O-:32])[O:13][CH2:31][CH2:14][CH:30]([CH3:16])[CH2:17][CH2:19][CH:20]=[C:24]([CH3:8])[CH2:29][CH2:28][CH:27]=[C:26]([CH3:3])[CH2:25][CH2:23][CH:22]=[C:21]([CH3:4])[CH2:18][CH2:15][CH:2]=[C:5]([CH3:6])[CH3:12].[O:34]=[P:33]([O-:35])([O-:7])[OH:1].[H+:37]</AAM>
      <SCORE>3</SCORE>
      <CHAOS>0 &lt;=&gt; 7</CHAOS>
      <SIGMA>0</SIGMA>
      <ENERGY>6.7E02</ENERGY>
      <DELTA>11E02</DELTA>
    </MAPPING>
    <MAPPING ALGORTIHM="Max-Mixture Model">
      <AAM>[O:34]=[P:33]([O-:35])([O-:7])[O:32][P:10](=[O:11])([O-:9])[O:13][CH2:31][CH2:14][CH:30]([CH3:16])[CH2:17][CH2:19][CH:20]=[C:24]([CH3:8])[CH2:29][CH2:28][CH:27]=[C:26]([CH3:3])[CH2:25][CH2:23][CH:22]=[C:21]([CH3:4])[CH2:18][CH2:15][CH:2]=[C:5]([CH3:6])[CH3:12].[H:37][OH:1]&gt;&gt;[O:11]=[P:10]([O-:9])([O-:32])[O:13][CH2:31][CH2:14][CH:30]([CH3:16])[CH2:17][CH2:19][CH:20]=[C:24]([CH3:8])[CH2:29][CH2:28][CH:27]=[C:26]([CH3:3])[CH2:25][CH2:23][CH:22]=[C:21]([CH3:4])[CH2:18][CH2:15][CH:2]=[C:5]([CH3:6])[CH3:12].[O:34]=[P:33]([O-:35])([O-:7])[OH:1].[H+:37]</AAM>
      <SCORE>3</SCORE>
      <CHAOS>0 &lt;=&gt; 7</CHAOS>
      <SIGMA>0</SIGMA>
      <ENERGY>6.7E02</ENERGY>
      <DELTA>11E02</DELTA>
    </MAPPING>
    <MAPPING ALGORTIHM="Ring Conservation Model">
      <AAM>[O:34]=[P:33]([O-:35])([O-:7])[O:32][P:10](=[O:11])([O-:9])[O:13][CH2:31][CH2:14][CH:30]([CH3:16])[CH2:17][CH2:19][CH:20]=[C:24]([CH3:8])[CH2:29][CH2:28][CH:27]=[C:26]([CH3:3])[CH2:25][CH2:23][CH:22]=[C:21]([CH3:4])[CH2:18][CH2:15][CH:2]=[C:5]([CH3:6])[CH3:12].[H:37][OH:1]&gt;&gt;[O:11]=[P:10]([O-:9])([O-:32])[O:13][CH2:31][CH2:14][CH:30]([CH3:16])[CH2:17][CH2:19][CH:20]=[C:24]([CH3:8])[CH2:29][CH2:28][CH:27]=[C:26]([CH3:3])[CH2:25][CH2:23][CH:22]=[C:21]([CH3:4])[CH2:18][CH2:15][CH:2]=[C:5]([CH3:6])[CH3:12].[O:34]=[P:33]([O-:35])([O-:7])[OH:1].[H+:37]</AAM>
      <SCORE>3</SCORE>
      <CHAOS>0 &lt;=&gt; 7</CHAOS>
      <SIGMA>0</SIGMA>
      <ENERGY>6.7E02</ENERGY>
      <DELTA>11E02</DELTA>
    </MAPPING>
  </ANNOTATION>
</EC_BLAST>
