<?xml version="1.0" encoding="UTF-8"?><EC_BLAST>
  <ANNOTATION>
    <MAPPING STATUS="SELECTED">
      <AAM>[H:15][CH:1]([C:7](=[O:9])[O-:8])[C:2]([OH:6])([C:3](=[O:5])[O-:4])[CH2:10][C:13](=[O:11])[O-:12]&gt;&gt;[O:9]=[C:7]([O-:8])[CH:1]=[C:2]([C:3](=[O:5])[O-:4])[CH2:10][C:13](=[O:11])[O-:12].[H:15][OH:6]</AAM>
    </MAPPING>
    <MAPPING ALGORTIHM="Local Minimization Model">
      <AAM>[H:15][CH:1]([C:7](=[O:9])[O-:8])[C:2]([OH:6])([C:3](=[O:5])[O-:4])[CH2:10][C:13](=[O:11])[O-:12]&gt;&gt;[O:9]=[C:7]([O-:8])[CH:1]=[C:2]([C:3](=[O:5])[O-:4])[CH2:10][C:13](=[O:11])[O-:12].[H:15][OH:6]</AAM>
      <SCORE>4</SCORE>
      <CHAOS>0 &lt;=&gt; 4</CHAOS>
      <SIGMA>0</SIGMA>
      <ENERGY>3.6E02</ENERGY>
      <DELTA>12E02</DELTA>
    </MAPPING>
    <MAPPING ALGORTIHM="Global Maximization Model">
      <AAM>[H:18][CH:10]([C:13](=[O:11])[O-:12])[C:2]([OH:6])([C:3](=[O:5])[O-:4])[CH2:1][C:7](=[O:9])[O-:8]&gt;&gt;[O:11]=[C:13]([O-:12])[CH:10]=[C:2]([C:3](=[O:5])[O-:4])[CH2:1][C:7](=[O:9])[O-:8].[H:18][OH:6]</AAM>
      <SCORE>4</SCORE>
      <CHAOS>0 &lt;=&gt; 4</CHAOS>
      <SIGMA>0</SIGMA>
      <ENERGY>3.6E02</ENERGY>
      <DELTA>12E02</DELTA>
    </MAPPING>
    <MAPPING ALGORTIHM="Max-Mixture Model">
      <AAM>[H:18][CH:10]([C:13](=[O:11])[O-:12])[C:2]([OH:6])([C:3](=[O:5])[O-:4])[CH2:1][C:7](=[O:9])[O-:8]&gt;&gt;[O:11]=[C:13]([O-:12])[CH:10]=[C:2]([C:3](=[O:5])[O-:4])[CH2:1][C:7](=[O:9])[O-:8].[H:18][OH:6]</AAM>
      <SCORE>4</SCORE>
      <CHAOS>0 &lt;=&gt; 4</CHAOS>
      <SIGMA>0</SIGMA>
      <ENERGY>3.6E02</ENERGY>
      <DELTA>12E02</DELTA>
    </MAPPING>
    <MAPPING ALGORTIHM="Ring Conservation Model">
      <AAM>[H:15][CH:1]([C:7](=[O:9])[O-:8])[C:2]([OH:6])([C:3](=[O:5])[O-:4])[CH2:10][C:13](=[O:11])[O-:12]&gt;&gt;[O:9]=[C:7]([O-:8])[CH:1]=[C:2]([C:3](=[O:5])[O-:4])[CH2:10][C:13](=[O:11])[O-:12].[H:15][OH:6]</AAM>
      <SCORE>4</SCORE>
      <CHAOS>0 &lt;=&gt; 4</CHAOS>
      <SIGMA>0</SIGMA>
      <ENERGY>3.6E02</ENERGY>
      <DELTA>12E02</DELTA>
    </MAPPING>
  </ANNOTATION>
</EC_BLAST>
