<?xml version="1.0" encoding="UTF-8"?>
<EC_BLAST>
  <ANNOTATION>
    <MAPPING STATUS="SELECTED">
      <AAM>[H:80][CH2:32][CH:30]([OH:24])[C:2](=[O:16])[S:6][CH2:4][CH2:42][NH:7][C:8](=[O:43])[CH2:50][CH2:9][NH:31][C:11](=[O:28])[CH:36]([OH:45])[C:13]([CH3:3])([CH3:14])[CH2:27][O:48][P:39](=[O:20])([O-:33])[O:18][P:21](=[O:1])([O-:26])[O:53][CH2:25][CH:40]1[O:5][CH:10]([n:34]2[cH:23][n:37][c:35]3[c:46]([n:12][cH:19][n:15][c:41]32)[NH2:47])[CH:44]([OH:22])[CH:17]1[O:49][P:29](=[O:51])([O-:38])[O-:52]&gt;&gt;[O:16]=[C:2]([S:6][CH2:4][CH2:42][NH:7][C:8](=[O:43])[CH2:50][CH2:9][NH:31][C:11](=[O:28])[CH:36]([OH:45])[C:13]([CH3:3])([CH3:14])[CH2:27][O:48][P:39](=[O:20])([O-:33])[O:18][P:21](=[O:1])([O-:26])[O:53][CH2:25][CH:40]1[O:5][CH:10]([n:34]2[cH:23][n:37][c:35]3[c:46]([n:12][cH:19][n:15][c:41]32)[NH2:47])[CH:44]([OH:22])[CH:17]1[O:49][P:29](=[O:51])([O-:38])[O-:52])[CH:30]=[CH2:32].[H:80][OH:24]</AAM>
    </MAPPING>
    <MAPPING ALGORTIHM="Local Minimization Model">
      <AAM>[H:80][CH2:32][CH:30]([OH:24])[C:2](=[O:16])[S:6][CH2:4][CH2:42][NH:7][C:8](=[O:43])[CH2:50][CH2:9][NH:31][C:11](=[O:28])[CH:36]([OH:45])[C:13]([CH3:3])([CH3:14])[CH2:27][O:48][P:39](=[O:20])([O-:33])[O:18][P:21](=[O:1])([O-:26])[O:53][CH2:25][CH:40]1[O:5][CH:10]([n:34]2[cH:23][n:37][c:35]3[c:46]([n:12][cH:19][n:15][c:41]32)[NH2:47])[CH:44]([OH:22])[CH:17]1[O:49][P:29](=[O:51])([O-:38])[O-:52]&gt;&gt;[O:16]=[C:2]([S:6][CH2:4][CH2:42][NH:7][C:8](=[O:43])[CH2:50][CH2:9][NH:31][C:11](=[O:28])[CH:36]([OH:45])[C:13]([CH3:3])([CH3:14])[CH2:27][O:48][P:39](=[O:20])([O-:33])[O:18][P:21](=[O:1])([O-:26])[O:53][CH2:25][CH:40]1[O:5][CH:10]([n:34]2[cH:23][n:37][c:35]3[c:46]([n:12][cH:19][n:15][c:41]32)[NH2:47])[CH:44]([OH:22])[CH:17]1[O:49][P:29](=[O:51])([O-:38])[O-:52])[CH:30]=[CH2:32].[H:80][OH:24]</AAM>
      <SCORE>4</SCORE>
      <CHAOS>0 &lt;=&gt; 4</CHAOS>
      <SIGMA>0</SIGMA>
      <ENERGY>3.6E02</ENERGY>
      <DELTA>12E02</DELTA>
    </MAPPING>
    <MAPPING ALGORTIHM="Global Maximization Model">
      <AAM>[H:80][CH2:32][CH:30]([OH:24])[C:2](=[O:16])[S:6][CH2:4][CH2:42][NH:7][C:8](=[O:43])[CH2:50][CH2:9][NH:31][C:11](=[O:28])[CH:36]([OH:45])[C:13]([CH3:3])([CH3:14])[CH2:27][O:48][P:39](=[O:20])([O-:33])[O:18][P:21](=[O:1])([O-:26])[O:53][CH2:25][CH:40]1[O:5][CH:10]([n:34]2[cH:23][n:37][c:35]3[c:46]([n:12][cH:19][n:15][c:41]32)[NH2:47])[CH:44]([OH:22])[CH:17]1[O:49][P:29](=[O:51])([O-:38])[O-:52]&gt;&gt;[O:16]=[C:2]([S:6][CH2:4][CH2:42][NH:7][C:8](=[O:43])[CH2:50][CH2:9][NH:31][C:11](=[O:28])[CH:36]([OH:45])[C:13]([CH3:3])([CH3:14])[CH2:27][O:48][P:39](=[O:20])([O-:33])[O:18][P:21](=[O:1])([O-:26])[O:53][CH2:25][CH:40]1[O:5][CH:10]([n:34]2[cH:23][n:37][c:35]3[c:46]([n:12][cH:19][n:15][c:41]32)[NH2:47])[CH:44]([OH:22])[CH:17]1[O:49][P:29](=[O:51])([O-:38])[O-:52])[CH:30]=[CH2:32].[H:80][OH:24]</AAM>
      <SCORE>4</SCORE>
      <CHAOS>0 &lt;=&gt; 4</CHAOS>
      <SIGMA>0</SIGMA>
      <ENERGY>3.6E02</ENERGY>
      <DELTA>12E02</DELTA>
    </MAPPING>
    <MAPPING ALGORTIHM="Max-Mixture Model">
      <AAM>[H:80][CH2:32][CH:30]([OH:24])[C:2](=[O:16])[S:6][CH2:4][CH2:42][NH:7][C:8](=[O:43])[CH2:50][CH2:9][NH:31][C:11](=[O:28])[CH:36]([OH:45])[C:13]([CH3:3])([CH3:14])[CH2:27][O:48][P:39](=[O:20])([O-:33])[O:18][P:21](=[O:1])([O-:26])[O:53][CH2:25][CH:40]1[O:5][CH:10]([n:34]2[cH:23][n:37][c:35]3[c:46]([n:12][cH:19][n:15][c:41]32)[NH2:47])[CH:44]([OH:22])[CH:17]1[O:49][P:29](=[O:51])([O-:38])[O-:52]&gt;&gt;[O:16]=[C:2]([S:6][CH2:4][CH2:42][NH:7][C:8](=[O:43])[CH2:50][CH2:9][NH:31][C:11](=[O:28])[CH:36]([OH:45])[C:13]([CH3:3])([CH3:14])[CH2:27][O:48][P:39](=[O:20])([O-:33])[O:18][P:21](=[O:1])([O-:26])[O:53][CH2:25][CH:40]1[O:5][CH:10]([n:34]2[cH:23][n:37][c:35]3[c:46]([n:12][cH:19][n:15][c:41]32)[NH2:47])[CH:44]([OH:22])[CH:17]1[O:49][P:29](=[O:51])([O-:38])[O-:52])[CH:30]=[CH2:32].[H:80][OH:24]</AAM>
      <SCORE>4</SCORE>
      <CHAOS>0 &lt;=&gt; 4</CHAOS>
      <SIGMA>0</SIGMA>
      <ENERGY>3.6E02</ENERGY>
      <DELTA>12E02</DELTA>
    </MAPPING>
    <MAPPING ALGORTIHM="Ring Conservation Model">
      <AAM>[H:80][CH2:32][CH:30]([OH:24])[C:2](=[O:16])[S:6][CH2:4][CH2:42][NH:7][C:8](=[O:43])[CH2:50][CH2:9][NH:31][C:11](=[O:28])[CH:36]([OH:45])[C:13]([CH3:3])([CH3:14])[CH2:27][O:48][P:39](=[O:20])([O-:33])[O:18][P:21](=[O:1])([O-:26])[O:53][CH2:25][CH:40]1[O:5][CH:10]([n:34]2[cH:23][n:37][c:35]3[c:46]([n:12][cH:19][n:15][c:41]32)[NH2:47])[CH:44]([OH:22])[CH:17]1[O:49][P:29](=[O:51])([O-:38])[O-:52]&gt;&gt;[O:16]=[C:2]([S:6][CH2:4][CH2:42][NH:7][C:8](=[O:43])[CH2:50][CH2:9][NH:31][C:11](=[O:28])[CH:36]([OH:45])[C:13]([CH3:3])([CH3:14])[CH2:27][O:48][P:39](=[O:20])([O-:33])[O:18][P:21](=[O:1])([O-:26])[O:53][CH2:25][CH:40]1[O:5][CH:10]([n:34]2[cH:23][n:37][c:35]3[c:46]([n:12][cH:19][n:15][c:41]32)[NH2:47])[CH:44]([OH:22])[CH:17]1[O:49][P:29](=[O:51])([O-:38])[O-:52])[CH:30]=[CH2:32].[H:80][OH:24]</AAM>
      <SCORE>4</SCORE>
      <CHAOS>0 &lt;=&gt; 4</CHAOS>
      <SIGMA>0</SIGMA>
      <ENERGY>3.6E02</ENERGY>
      <DELTA>12E02</DELTA>
    </MAPPING>
  </ANNOTATION>
</EC_BLAST>
