<?xml version="1.0" encoding="UTF-8"?><EC_BLAST>
  <ANNOTATION>
    <MAPPING STATUS="SELECTED">
      <AAM>[O:31]=[P:30]([O-:29])([O-:6])[O:28][P:26](=[O:25])([O-:27])[O:24][P:22](=[O:21])([O-:23])[O:20][CH2:19][CH:1]1[O:7][CH:8]([n:9]2[cH:10][n:15][c:11]3[c:16]([n:17][cH:18][n:14][c:12]32)[NH2:13])[CH:3]([OH:2])[CH:4]1[OH:5].[H:95][n:59]1[c:57](=[O:58])[nH:54][c:55](=[O:56])[c:53]2[n:60][cH:52][n:51]([c:61]12)[CH:50]3[O:49][CH:43]([CH2:62][O:63][P:65](=[O:66])([O-:64])[O-:48])[CH:46]([OH:47])[CH:45]3[OH:44].[O:39]=[C:38]([O-:40])[CH:36]([NH3+:41])[CH2:34][CH2:32][C:35](=[O:33])[NH2:37].[H:90][OH:42]&gt;&gt;[O:56]=[c:55]1[nH:54][c:57]([n:59][c:61]2[c:53]1[n:60][cH:52][n:51]2[CH:50]3[O:49][CH:43]([CH2:62][O:63][P:65](=[O:66])([O-:48])[O-:64])[CH:46]([OH:47])[CH:45]3[OH:44])[NH2:37].[O:21]=[P:22]([O-:23])([O-:24])[O:20][CH2:19][CH:1]1[O:7][CH:8]([n:9]2[cH:10][n:15][c:11]3[c:16]([n:17][cH:18][n:14][c:12]32)[NH2:13])[CH:3]([OH:2])[CH:4]1[OH:5].[O:33]=[C:35]([O-:58])[CH2:32][CH2:34][CH:36]([C:38](=[O:39])[O-:40])[NH3+:41].[O:31]=[P:30]([O-:29])([O-:6])[O:28][P:26](=[O:25])([O-:27])[OH:42].[H+:95].[H+:90]</AAM>
    </MAPPING>
    <MAPPING ALGORTIHM="Local Minimization Model">
      <AAM>[O:66]=[P:65]([O-:64])([O-:41])[O:63][P:61](=[O:60])([O-:62])[O:59][P:57](=[O:56])([O-:58])[O:55][CH2:54][CH:36]1[O:42][CH:43]([n:44]2[cH:45][n:50][c:46]3[c:51]([n:52][cH:53][n:49][c:47]32)[NH2:48])[CH:38]([OH:37])[CH:39]1[OH:40].[H:73][n:18]1[c:16](=[O:17])[nH:13][c:14](=[O:15])[c:12]2[n:19][cH:11][n:10]([c:20]12)[CH:9]3[O:8][CH:2]([CH2:21][O:22][P:24](=[O:25])([O-:23])[O-:7])[CH:5]([OH:6])[CH:4]3[OH:3].[O:33]=[C:32]([O-:34])[CH:30]([NH3+:35])[CH2:28][CH2:26][C:29](=[O:27])[NH2:31].[H:67][O:1][H:68]&gt;&gt;[O:15]=[c:14]1[nH:13][c:16]([n:18][c:20]2[c:12]1[n:19][cH:11][n:10]2[CH:9]3[O:8][CH:2]([CH2:21][O:22][P:24](=[O:25])([O-:7])[O-:23])[CH:5]([OH:6])[CH:4]3[OH:3])[NH2:31].[O:56]=[P:57]([O-:1])([O-:58])[O:55][CH2:54][CH:36]1[O:42][CH:43]([n:44]2[cH:45][n:50][c:46]3[c:51]([n:52][cH:53][n:49][c:47]32)[NH2:48])[CH:38]([OH:37])[CH:39]1[OH:40].[O:27]=[C:29]([O-:17])[CH2:26][CH2:28][CH:30]([C:32](=[O:33])[O-:34])[NH3+:35].[H:73][O:59][P:61](=[O:60])([O-:62])[O:63][P:65](=[O:66])([O-:64])[O-:41].[H+:67].[H+:68]</AAM>
      <SCORE>10</SCORE>
      <CHAOS>0 &lt;=&gt; 22</CHAOS>
      <SIGMA>0</SIGMA>
      <ENERGY>24E02</ENERGY>
      <DELTA>42E02</DELTA>
    </MAPPING>
    <MAPPING ALGORTIHM="Global Maximization Model">
      <AAM>[O:31]=[P:30]([O-:29])([O-:6])[O:28][P:26](=[O:25])([O-:27])[O:24][P:22](=[O:21])([O-:23])[O:20][CH2:19][CH:1]1[O:7][CH:8]([n:9]2[cH:10][n:15][c:11]3[c:16]([n:17][cH:18][n:14][c:12]32)[NH2:13])[CH:3]([OH:2])[CH:4]1[OH:5].[H:95][n:59]1[c:57](=[O:58])[nH:54][c:55](=[O:56])[c:53]2[n:60][cH:52][n:51]([c:61]12)[CH:50]3[O:49][CH:43]([CH2:62][O:63][P:65](=[O:66])([O-:64])[O-:48])[CH:46]([OH:47])[CH:45]3[OH:44].[O:39]=[C:38]([O-:40])[CH:36]([NH3+:41])[CH2:34][CH2:32][C:35](=[O:33])[NH2:37].[H:90][OH:42]&gt;&gt;[O:56]=[c:55]1[nH:54][c:57]([n:59][c:61]2[c:53]1[n:60][cH:52][n:51]2[CH:50]3[O:49][CH:43]([CH2:62][O:63][P:65](=[O:66])([O-:48])[O-:64])[CH:46]([OH:47])[CH:45]3[OH:44])[NH2:37].[O:21]=[P:22]([O-:23])([O-:24])[O:20][CH2:19][CH:1]1[O:7][CH:8]([n:9]2[cH:10][n:15][c:11]3[c:16]([n:17][cH:18][n:14][c:12]32)[NH2:13])[CH:3]([OH:2])[CH:4]1[OH:5].[O:33]=[C:35]([O-:58])[CH2:32][CH2:34][CH:36]([C:38](=[O:39])[O-:40])[NH3+:41].[O:31]=[P:30]([O-:29])([O-:6])[O:28][P:26](=[O:25])([O-:27])[OH:42].[H+:95].[H+:90]</AAM>
      <SCORE>8</SCORE>
      <CHAOS>0 &lt;=&gt; 20</CHAOS>
      <SIGMA>0</SIGMA>
      <ENERGY>24E02</ENERGY>
      <DELTA>33E02</DELTA>
    </MAPPING>
    <MAPPING ALGORTIHM="Max-Mixture Model">
      <AAM>[O:65]=[P:64]([O-:63])([O-:40])[O:62][P:60](=[O:59])([O-:61])[O:58][P:56](=[O:55])([O-:57])[O:54][CH2:53][CH:35]1[O:41][CH:42]([n:43]2[cH:44][n:49][c:45]3[c:50]([n:51][cH:52][n:48][c:46]32)[NH2:47])[CH:37]([OH:36])[CH:38]1[OH:39].[H:81][n:27]1[c:25](=[O:26])[nH:22][c:23](=[O:24])[c:21]2[n:28][cH:20][n:19]([c:29]12)[CH:18]3[O:17][CH:11]([CH2:30][O:31][P:33](=[O:34])([O-:32])[O-:16])[CH:14]([OH:15])[CH:13]3[OH:12].[O:8]=[C:7]([O-:9])[CH:5]([NH3+:10])[CH2:3][CH2:1][C:4](=[O:2])[NH2:6].[H:101][OH:66]&gt;&gt;[O:24]=[c:23]1[nH:22][c:25]([n:27][c:29]2[c:21]1[n:28][cH:20][n:19]2[CH:18]3[O:17][CH:11]([CH2:30][O:31][P:33](=[O:34])([O-:16])[O-:32])[CH:14]([OH:15])[CH:13]3[OH:12])[NH2:6].[O:55]=[P:56]([O-:57])([O-:58])[O:54][CH2:53][CH:35]1[O:41][CH:42]([n:43]2[cH:44][n:49][c:45]3[c:50]([n:51][cH:52][n:48][c:46]32)[NH2:47])[CH:37]([OH:36])[CH:38]1[OH:39].[O:2]=[C:4]([O-:26])[CH2:1][CH2:3][CH:5]([C:7](=[O:8])[O-:9])[NH3+:10].[O:65]=[P:64]([O-:63])([O-:40])[O:62][P:60](=[O:59])([O-:61])[OH:66].[H+:81].[H+:101]</AAM>
      <SCORE>8</SCORE>
      <CHAOS>0 &lt;=&gt; 20</CHAOS>
      <SIGMA>0</SIGMA>
      <ENERGY>24E02</ENERGY>
      <DELTA>33E02</DELTA>
    </MAPPING>
    <MAPPING ALGORTIHM="Ring Conservation Model">
      <AAM>[O:31]=[P:30]([O-:29])([O-:6])[O:28][P:26](=[O:25])([O-:27])[O:24][P:22](=[O:21])([O-:23])[O:20][CH2:19][CH:1]1[O:7][CH:8]([n:9]2[cH:10][n:15][c:11]3[c:16]([n:17][cH:18][n:14][c:12]32)[NH2:13])[CH:3]([OH:2])[CH:4]1[OH:5].[H:95][n:59]1[c:57](=[O:58])[nH:54][c:55](=[O:56])[c:53]2[n:60][cH:52][n:51]([c:61]12)[CH:50]3[O:49][CH:43]([CH2:62][O:63][P:65](=[O:66])([O-:64])[O-:48])[CH:46]([OH:47])[CH:45]3[OH:44].[O:39]=[C:38]([O-:40])[CH:36]([NH3+:41])[CH2:34][CH2:32][C:35](=[O:33])[NH2:37].[H:90][OH:42]&gt;&gt;[O:56]=[c:55]1[nH:54][c:57]([n:59][c:61]2[c:53]1[n:60][cH:52][n:51]2[CH:50]3[O:49][CH:43]([CH2:62][O:63][P:65](=[O:66])([O-:48])[O-:64])[CH:46]([OH:47])[CH:45]3[OH:44])[NH2:37].[O:21]=[P:22]([O-:27])([O-:24])[O:20][CH2:19][CH:1]1[O:7][CH:8]([n:9]2[cH:10][n:15][c:11]3[c:16]([n:17][cH:18][n:14][c:12]32)[NH2:13])[CH:3]([OH:2])[CH:4]1[OH:5].[O:33]=[C:35]([O-:23])[CH2:32][CH2:34][CH:36]([C:38](=[O:39])[O-:40])[NH3+:41].[O:31]=[P:30]([O-:29])([O-:6])[O:28][P:26](=[O:58])([O-:25])[OH:42].[H+:95].[H+:90]</AAM>
      <SCORE>13</SCORE>
      <CHAOS>0 &lt;=&gt; 24</CHAOS>
      <SIGMA>0</SIGMA>
      <ENERGY>40E02</ENERGY>
      <DELTA>48E02</DELTA>
    </MAPPING>
  </ANNOTATION>
</EC_BLAST>
